cylestio_monitor/__init__.py
cylestio_monitor/api_client.py
cylestio_monitor/exceptions.py
cylestio_monitor/monitor.py
cylestio_monitor/_compat/__init__.py
cylestio_monitor/_compat/langchain.py
cylestio_monitor/_compat/utils.py
cylestio_monitor/config/README.md
cylestio_monitor/config/__init__.py
cylestio_monitor/config/config_manager.py
cylestio_monitor/config/utils.py
cylestio_monitor/event_logger/__init__.py
cylestio_monitor/events/README.md
cylestio_monitor/events/__init__.py
cylestio_monitor/events/deduplication.py
cylestio_monitor/events/factories.py
cylestio_monitor/events/processor.py
cylestio_monitor/events/registry.py
cylestio_monitor/events/schema.py
cylestio_monitor/events/standardized_event.py
cylestio_monitor/events/converters/__init__.py
cylestio_monitor/events/converters/anthropic.py
cylestio_monitor/events/converters/base.py
cylestio_monitor/events/converters/default.py
cylestio_monitor/events/converters/factory.py
cylestio_monitor/events/converters/langchain.py
cylestio_monitor/events/converters/langgraph.py
cylestio_monitor/events/converters/mcp.py
cylestio_monitor/events/converters/openai.py
cylestio_monitor/events/converters/default/__init__.py
cylestio_monitor/events/converters/default/converter.py
cylestio_monitor/events/converters/default/extractors.py
cylestio_monitor/events/converters/default/standardizer.py
cylestio_monitor/events/keyword_detection/__init__.py
cylestio_monitor/events/keyword_detection/text_processing.py
cylestio_monitor/events/processing/__init__.py
cylestio_monitor/events/processing/hooks.py
cylestio_monitor/events/processing/logger.py
cylestio_monitor/events/processing/mcp.py
cylestio_monitor/events/processing/processor.py
cylestio_monitor/events/processing/security.py
cylestio_monitor/events/processors/__init__.py
cylestio_monitor/events/processors/event_processor.py
cylestio_monitor/events_processor/__init__.py
cylestio_monitor/patchers/README.md
cylestio_monitor/patchers/__init__.py
cylestio_monitor-0.1.12.dist-info/METADATA
cylestio_monitor-0.1.12.dist-info/WHEEL
cylestio_monitor-0.1.12.dist-info/licenses/LICENSE
cylestio_monitor-0.1.12.dist-info/RECORD
