Metadata-Version: 2.4
Name: cylestio-monitor
Version: 0.1.12
Summary: A monitoring tool for LLM API calls
Project-URL: Homepage, https://github.com/cylestio/cylestio-monitor
Project-URL: Bug Tracker, https://github.com/cylestio/cylestio-monitor/issues
Project-URL: Documentation, https://github.com/cylestio/cylestio-monitor#readme
Project-URL: Changelog, https://github.com/cylestio/cylestio-monitor/blob/main/CHANGELOG.md
Project-URL: Source, https://github.com/cylestio/cylestio-monitor
Author-email: "Cylestio.com" <contact@Cylestio.com>
License-Expression: MIT
License-File: LICENSE
Keywords: api,compliance,llm,monitoring,security
Classifier: Development Status :: 4 - Beta
Classifier: Intended Audience :: Developers
Classifier: License :: OSI Approved :: MIT License
Classifier: Programming Language :: Python :: 3.12
Classifier: Topic :: Security
Classifier: Topic :: Software Development :: Libraries :: Python Modules
Classifier: Topic :: System :: Monitoring
Requires-Python: >=3.12
Requires-Dist: anthropic>=0.18.0
Requires-Dist: langchain-core>=0.1.0
Requires-Dist: langchain>=0.1.0
Requires-Dist: mcp>=1.3.0
Requires-Dist: platformdirs>=4.0.0
Requires-Dist: pydantic>=2.0.0
Requires-Dist: python-dotenv>=1.0.0
Requires-Dist: pyyaml>=6.0.0
Requires-Dist: requests>=2.31.0
Requires-Dist: setuptools>=68.0.0
Requires-Dist: structlog>=24.1.0
Provides-Extra: security
Requires-Dist: bandit>=1.7.0; extra == 'security'
Requires-Dist: dependency-check>=0.7.0; extra == 'security'
Requires-Dist: detect-secrets>=1.4.0; extra == 'security'
Requires-Dist: pip-audit>=2.7.0; extra == 'security'
Requires-Dist: pre-commit>=3.5.0; extra == 'security'
Requires-Dist: semgrep>=1.48.0; extra == 'security'
Requires-Dist: sentence-transformers>=3.1.0; extra == 'security'
Provides-Extra: test
Requires-Dist: coverage>=7.4.0; extra == 'test'
Requires-Dist: pytest-asyncio>=0.23.0; extra == 'test'
Requires-Dist: pytest-cov>=4.1.0; extra == 'test'
Requires-Dist: pytest-mock>=3.12.0; extra == 'test'
Requires-Dist: pytest>=8.0.0; extra == 'test'
